openapi_client/__init__.py
openapi_client/api_client.py
openapi_client/api_response.py
openapi_client/configuration.py
openapi_client/exceptions.py
openapi_client/py.typed
openapi_client/rest.py
openapi_client/api/__init__.py
openapi_client/api/assays_api.py
openapi_client/api/collections_api.py
openapi_client/api/content_blobs_api.py
openapi_client/api/create_api.py
openapi_client/api/data_files_api.py
openapi_client/api/delete_api.py
openapi_client/api/documents_api.py
openapi_client/api/download_api.py
openapi_client/api/events_api.py
openapi_client/api/extended_metadata_types_api.py
openapi_client/api/institutions_api.py
openapi_client/api/investigations_api.py
openapi_client/api/list_api.py
openapi_client/api/models_api.py
openapi_client/api/organisms_api.py
openapi_client/api/people_api.py
openapi_client/api/presentations_api.py
openapi_client/api/programmes_api.py
openapi_client/api/projects_api.py
openapi_client/api/publications_api.py
openapi_client/api/read_api.py
openapi_client/api/sample_attribute_types_api.py
openapi_client/api/sample_types_api.py
openapi_client/api/samples_api.py
openapi_client/api/search_api.py
openapi_client/api/sops_api.py
openapi_client/api/studies_api.py
openapi_client/api/update_api.py
openapi_client/api/upload_api.py
openapi_client/api/workflows_api.py
openapi_client/models/__init__.py
openapi_client/models/access_types.py
openapi_client/models/any_skeleton.py
openapi_client/models/any_skeleton_attributes.py
openapi_client/models/any_type.py
openapi_client/models/assay_attributes.py
openapi_client/models/assay_attributes_assay_class.py
openapi_client/models/assay_attributes_assay_type.py
openapi_client/models/assay_attributes_technology_type.py
openapi_client/models/assay_patch.py
openapi_client/models/assay_patch_data.py
openapi_client/models/assay_patch_data_attributes.py
openapi_client/models/assay_patch_data_relationships.py
openapi_client/models/assay_post.py
openapi_client/models/assay_post_data.py
fairdomseek_openapi_client-1.0.0.dist-info/METADATA
fairdomseek_openapi_client-1.0.0.dist-info/WHEEL
fairdomseek_openapi_client-1.0.0.dist-info/top_level.txt
fairdomseek_openapi_client-1.0.0.dist-info/RECORD
