Metadata-Version: 2.4
Name: fairdomseek-openapi-client
Version: 1.0.0
Summary: JSON API to FAIRDOM SEEK
Home-page: 
Author: SEEK support
Author-email: support@fair-dom.org
License: The 3-Clause BSD License
Keywords: OpenAPI,OpenAPI-Generator,JSON API to FAIRDOM SEEK
Requires-Dist: urllib3<3.0.0,>=2.1.0
Requires-Dist: python-dateutil>=2.8.2
Requires-Dist: pydantic>=2
Requires-Dist: typing-extensions>=4.7.1
Dynamic: author
Dynamic: author-email
Dynamic: description
Dynamic: description-content-type
Dynamic: keywords
Dynamic: license
Dynamic: requires-dist
Dynamic: summary
